[{"nome":"AGUA BRANCA"},{"nome":"AGUIAR"},{"nome":"ALAGOA GRANDE"},{"nome":"ALAGOA NOVA"},{"nome":"ALAGOINHA"},{"nome":"ALCANTIL"},{"nome":"ALGODAO DE JANDAIRA"},{"nome":"ALHANDRA"},{"nome":"SAO JOAO DO RIO DO PEIXE"},{"nome":"AMPARO"},{"nome":"APARECIDA"},{"nome":"ARACAGI"},{"nome":"ARARA"},{"nome":"ARARUNA"},{"nome":"AREIA"},{"nome":"AREIA DE BARAUNAS"},{"nome":"AREIAL"},{"nome":"AROEIRAS"},{"nome":"ASSUNCAO"},{"nome":"BAIA DA TRAICAO"},{"nome":"BANANEIRAS"},{"nome":"BARAUNA"},{"nome":"BARRA DE SANTANA"},{"nome":"BARRA DE SANTA ROSA"},{"nome":"BARRA DE SAO MIGUEL"},{"nome":"BAYEUX"},{"nome":"BELEM"},{"nome":"BELEM DO BREJO DO CRUZ"},{"nome":"BERNARDINO BATISTA"},{"nome":"BOA VENTURA"},{"nome":"BOA VISTA"},{"nome":"BOM JESUS"},{"nome":"BOM SUCESSO"},{"nome":"BONITO DE SANTA FE"},{"nome":"BOQUEIRAO"},{"nome":"IGARACY"},{"nome":"BORBOREMA"},{"nome":"BREJO DO CRUZ"},{"nome":"BREJO DOS SANTOS"},{"nome":"CAAPORA"},{"nome":"CABACEIRAS"},{"nome":"CABEDELO"},{"nome":"CACHOEIRA DOS INDIOS"},{"nome":"CACIMBA DE AREIA"},{"nome":"CACIMBA DE DENTRO"},{"nome":"CACIMBAS"},{"nome":"CAICARA"},{"nome":"CAJAZEIRAS"},{"nome":"CAJAZEIRINHAS"},{"nome":"CALDAS BRANDAO"},{"nome":"CAMALAU"},{"nome":"CAMPINA GRANDE"},{"nome":"CAPIM"},{"nome":"CARAUBAS"},{"nome":"CARRAPATEIRA"},{"nome":"CASSERENGUE"},{"nome":"CATINGUEIRA"},{"nome":"CATOLE DO ROCHA"},{"nome":"CATURITE"},{"nome":"CONCEICAO"},{"nome":"CONDADO"},{"nome":"CONDE"},{"nome":"CONGO"},{"nome":"COREMAS"},{"nome":"COXIXOLA"},{"nome":"CRUZ DO ESPIRITO SANTO"},{"nome":"CUBATI"},{"nome":"CUITE"},{"nome":"CUITEGI"},{"nome":"CUITE DE MAMANGUAPE"},{"nome":"CURRAL DE CIMA"},{"nome":"CURRAL VELHO"},{"nome":"DAMIAO"},{"nome":"DESTERRO"},{"nome":"VISTA SERRANA"},{"nome":"DIAMANTE"},{"nome":"DONA INES"},{"nome":"DUAS ESTRADAS"},{"nome":"EMAS"},{"nome":"ESPERANCA"},{"nome":"FAGUNDES"},{"nome":"FREI MARTINHO"},{"nome":"GADO BRAVO"},{"nome":"GUARABIRA"},{"nome":"GURINHEM"},{"nome":"GURJAO"},{"nome":"IBIARA"},{"nome":"IMACULADA"},{"nome":"INGA"},{"nome":"ITABAIANA"},{"nome":"ITAPORANGA"},{"nome":"ITAPOROROCA"},{"nome":"ITATUBA"},{"nome":"JACARAU"},{"nome":"JERICO"},{"nome":"JOAO PESSOA"},{"nome":"JUAREZ TAVORA"},{"nome":"JUAZEIRINHO"},{"nome":"JUNCO DO SERIDO"},{"nome":"JURIPIRANGA"},{"nome":"JURU"},{"nome":"LAGOA"},{"nome":"LAGOA DE DENTRO"},{"nome":"LAGOA SECA"},{"nome":"LASTRO"},{"nome":"LIVRAMENTO"},{"nome":"LOGRADOURO"},{"nome":"LUCENA"},{"nome":"MAE D AGUA"},{"nome":"MALTA"},{"nome":"MAMANGUAPE"},{"nome":"MANAIRA"},{"nome":"MARCACAO"},{"nome":"MARI"},{"nome":"MARIZOPOLIS"},{"nome":"MASSARANDUBA"},{"nome":"MATARACA"},{"nome":"MATINHAS"},{"nome":"MATO GROSSO"},{"nome":"MATUREIA"},{"nome":"MOGEIRO"},{"nome":"MONTADAS"},{"nome":"MONTE HOREBE"},{"nome":"MONTEIRO"},{"nome":"MULUNGU"},{"nome":"NATUBA"},{"nome":"NAZAREZINHO"},{"nome":"NOVA FLORESTA"},{"nome":"NOVA OLINDA"},{"nome":"NOVA PALMEIRA"},{"nome":"OLHO D AGUA"},{"nome":"OLIVEDOS"},{"nome":"OURO VELHO"},{"nome":"PARARI"},{"nome":"PASSAGEM"},{"nome":"PATOS"},{"nome":"PAULISTA"},{"nome":"PEDRA BRANCA"},{"nome":"PEDRA LAVRADA"},{"nome":"PEDRAS DE FOGO"},{"nome":"PIANCO"},{"nome":"PICUI"},{"nome":"PILAR"},{"nome":"PILOES"},{"nome":"PILOEZINHOS"},{"nome":"PIRPIRITUBA"},{"nome":"PITIMBU"},{"nome":"POCINHOS"},{"nome":"POCO DANTAS"},{"nome":"POCO DE JOSE DE MOURA"},{"nome":"POMBAL"},{"nome":"PRATA"},{"nome":"PRINCESA ISABEL"},{"nome":"PUXINANA"},{"nome":"QUEIMADAS"},{"nome":"QUIXABA"},{"nome":"REMIGIO"},{"nome":"PEDRO REGIS"},{"nome":"RIACHAO"},{"nome":"RIACHAO DO BACAMARTE"},{"nome":"RIACHAO DO POCO"},{"nome":"RIACHO DE SANTO ANTONIO"},{"nome":"RIACHO DOS CAVALOS"},{"nome":"RIO TINTO"},{"nome":"SALGADINHO"},{"nome":"SALGADO DE SAO FELIX"},{"nome":"SANTA CECILIA"},{"nome":"SANTA CRUZ"},{"nome":"SANTA HELENA"},{"nome":"SANTA INES"},{"nome":"SANTA LUZIA"},{"nome":"SANTANA DE MANGUEIRA"},{"nome":"SANTANA DOS GARROTES"},{"nome":"JOCA CLAUDINO"},{"nome":"SANTA RITA"},{"nome":"SANTA TERESINHA"},{"nome":"SANTO ANDRE"},{"nome":"SAO BENTO"},{"nome":"SAO BENTINHO"},{"nome":"SAO DOMINGOS DO CARIRI"},{"nome":"SAO DOMINGOS"},{"nome":"SAO FRANCISCO"},{"nome":"SAO JOAO DO CARIRI"},{"nome":"SAO JOAO DO TIGRE"},{"nome":"SAO JOSE DA LAGOA TAPADA"},{"nome":"SAO JOSE DE CAIANA"},{"nome":"SAO JOSE DE ESPINHARAS"},{"nome":"SAO JOSE DOS RAMOS"},{"nome":"SAO JOSE DE PIRANHAS"},{"nome":"SAO JOSE DE PRINCESA"},{"nome":"SAO JOSE DO BONFIM"},{"nome":"SAO JOSE DO BREJO DO CRUZ"},{"nome":"SAO JOSE DO SABUGI"},{"nome":"SAO JOSE DOS CORDEIROS"},{"nome":"SAO MAMEDE"},{"nome":"SAO MIGUEL DE TAIPU"},{"nome":"SAO SEBASTIAO DE LAGOA DE ROCA"},{"nome":"SAO SEBASTIAO DO UMBUZEIRO"},{"nome":"SAPE"},{"nome":"SERIDO"},{"nome":"SERRA BRANCA"},{"nome":"SERRA DA RAIZ"},{"nome":"SERRA GRANDE"},{"nome":"SERRA REDONDA"},{"nome":"SERRARIA"},{"nome":"SERTAOZINHO"},{"nome":"SOBRADO"},{"nome":"SOLANEA"},{"nome":"SOLEDADE"},{"nome":"SOSSEGO"},{"nome":"SOUSA"},{"nome":"SUME"},{"nome":"TACIMA"},{"nome":"TAPEROA"},{"nome":"TAVARES"},{"nome":"TEIXEIRA"},{"nome":"TENORIO"},{"nome":"TRIUNFO"},{"nome":"UIRAUNA"},{"nome":"UMBUZEIRO"},{"nome":"VARZEA"},{"nome":"VIEIROPOLIS"},{"nome":"ZABELE"}]